sqliteorm_py/__init__.py
sqliteorm_py/basemodel.py
sqliteorm_py/cli.py
sqliteorm_py/connect_to_db.py
sqliteorm_py/fields.py
sqliteorm_py/makemigrations.py
sqliteorm_py/templates/manage.py
sqliteorm_py/templates/models.py
sqliteorm_py/templates/settings.py
sqliteorm_py-0.0.5.dist-info/LICENSE
sqliteorm_py-0.0.5.dist-info/METADATA
sqliteorm_py-0.0.5.dist-info/WHEEL
sqliteorm_py-0.0.5.dist-info/entry_points.txt
sqliteorm_py-0.0.5.dist-info/top_level.txt
sqliteorm_py-0.0.5.dist-info/RECORD
